CHANGES.rst
MANIFEST.in
README.rst
setup.cfg
setup.py
cgrspy/__init__.py
cgrspy/cgrspy_bootstrap.cpp
cgrspy.egg-info/PKG-INFO
cgrspy.egg-info/SOURCES.txt
cgrspy.egg-info/dependency_links.txt
cgrspy.egg-info/top_level.txt
cgrspy/tests/__init__.py
cgrspy/tests/test_main.py