Metadata-Version: 1.0
Name: cgrspy
Version: 1.3.0
Summary: Python interface to the CellML Generics and Reflection Service
Home-page: http://cellml-api.sf.net/
Author: Andrew Miller
Author-email: ak.miller@auckland.ac.nz
License: GPL/LGPL/MPL
Platform: UNKNOWN
